MANIFEST.in
README.rst
setup.py
agon_ratings/__init__.py
agon_ratings/categories.py
agon_ratings/managers.py
agon_ratings/models.py
agon_ratings/urls.py
agon_ratings/views.py
agon_ratings.egg-info/PKG-INFO
agon_ratings.egg-info/SOURCES.txt
agon_ratings.egg-info/dependency_links.txt
agon_ratings.egg-info/not-zip-safe
agon_ratings.egg-info/top_level.txt
agon_ratings/static/agon_ratings/img/background.gif
agon_ratings/static/agon_ratings/img/cancel-off-big.png
agon_ratings/static/agon_ratings/img/cancel-off.png
agon_ratings/static/agon_ratings/img/cancel-on-big.png
agon_ratings/static/agon_ratings/img/cancel-on.png
agon_ratings/static/agon_ratings/img/coffee.png
agon_ratings/static/agon_ratings/img/face-a.png
agon_ratings/static/agon_ratings/img/face-b.png
agon_ratings/static/agon_ratings/img/face-c.png
agon_ratings/static/agon_ratings/img/face-d.png
agon_ratings/static/agon_ratings/img/face-off.png
agon_ratings/static/agon_ratings/img/medal-off.png
agon_ratings/static/agon_ratings/img/medal-on.png
agon_ratings/static/agon_ratings/img/star-half-big.png
agon_ratings/static/agon_ratings/img/star-half.png
agon_ratings/static/agon_ratings/img/star-off-big.png
agon_ratings/static/agon_ratings/img/star-off.png
agon_ratings/static/agon_ratings/img/star-on-big.png
agon_ratings/static/agon_ratings/img/star-on.png
agon_ratings/static/agon_ratings/js/ajax_csrf.js
agon_ratings/static/agon_ratings/js/jquery.raty.js
agon_ratings/templates/agon_ratings/_script.html
agon_ratings/templatetags/__init__.py
agon_ratings/templatetags/agon_ratings_tags.py