Metadata-Version: 1.0
Name: agon-ratings
Version: 0.2
Summary: a user ratings app
Home-page: http://github.com/eldarion/agon-ratings
Author: Eldarion
Author-email: developers@eldarion.com
License: BSD
Platform: UNKNOWN
Classifier: Development Status :: 3 - Alpha
Classifier: Environment :: Web Environment
Classifier: Intended Audience :: Developers
Classifier: License :: OSI Approved :: BSD License
Classifier: Operating System :: OS Independent
Classifier: Programming Language :: Python
Classifier: Framework :: Django
